pyelethos/__init__.py
pyelethos/pyelethos.py
pyelethos-0.0.1.7.dist-info/METADATA
pyelethos-0.0.1.7.dist-info/WHEEL
pyelethos-0.0.1.7.dist-info/top_level.txt
pyelethos-0.0.1.7.dist-info/RECORD
